{
  "profiles": {
    "npmjs": {
      "comment": "发布到 npmjs：仅打包 identity、git-commit、git-commit-msg、git-push 四个 skill",
      "publishConfig": {
        "registry": "https://registry.npmjs.org/"
      },
      "skills": ["identity", "git-commit", "git-commit-msg", "git-push"]
    },
    "kfz": {
      "comment": "发布到孔夫子私服：打包 monorepo 同步后的全部 skill；npm 包名与 npmjs 区分",
      "packageName": "kfz-skills-helper",
      "publishConfig": {
        "registry": "http://maven.kongfz.com/repository/npm_local/"
      },
      "skills": "all"
    }
  }
}
